sonification/__init__.py
sonification/chords.py
sonification/converters.py
sonification/sonify_scrap.py
sonification/util.py
sonification-0.0.10.dist-info/licenses/LICENSE
sonification-0.0.10.dist-info/METADATA
sonification-0.0.10.dist-info/WHEEL
sonification-0.0.10.dist-info/top_level.txt
sonification-0.0.10.dist-info/RECORD
