Metadata-Version: 2.4
Name: sonification
Version: 0.0.10
Summary: Map data to sound allowing it to be interpreted it in an auditory manner
Home-page: https://github.com/thorwhalen/sonification
Author: Thor Whalen
License: mit
Platform: any
License-File: LICENSE
Requires-Dist: tonal
Provides-Extra: testing
Dynamic: license-file
